ppropie/__init__.py
ppropie/utils.py
ppropie-0.0.3.dist-info/LICENSE
ppropie-0.0.3.dist-info/METADATA
ppropie-0.0.3.dist-info/WHEEL
ppropie-0.0.3.dist-info/top_level.txt
ppropie-0.0.3.dist-info/RECORD
